Metadata-Version: 1.0
Name: rdm-distributions
Version: 0.3
Summary: Gaussian and Binomial distributions (basics)
Home-page: UNKNOWN
Author: Roberto De Monte
Author-email: roberto.de.monte5@gmail.com
License: UNKNOWN
Platform: UNKNOWN
